subrink.py
subrink-0.1.0.dist-info/WHEEL
subrink-0.1.0.dist-info/METADATA
subrink-0.1.0.dist-info/RECORD
