Metadata-Version: 2.1
Name: subrink
Version: 0.1.0
Summary: Sum of two digits
Author: Brinkinvision
Author-email: brinkinvision@gmail.com
Requires-Python: >=3.6,<4.0
Classifier: Programming Language :: Python :: 3
Classifier: Programming Language :: Python :: 3.10
Classifier: Programming Language :: Python :: 3.6
Classifier: Programming Language :: Python :: 3.7
Classifier: Programming Language :: Python :: 3.8
Classifier: Programming Language :: Python :: 3.9
